dtflw/__init__.py
dtflw/arguments.py
dtflw/assertions.py
dtflw/com.py
dtflw/databricks.py
dtflw/display.py
dtflw/flow.py
dtflw/flow_context.py
dtflw/input_table.py
dtflw/lazy_notebook.py
dtflw/logger.py
dtflw/output_table.py
dtflw/pipeline.py
dtflw/plugin.py
dtflw/tables_repo.py
dtflw/storage/__init__.py
dtflw/storage/azure.py
dtflw/storage/dbfs.py
dtflw/storage/fs.py
dtflw-0.6.7.dist-info/LICENSE
dtflw-0.6.7.dist-info/METADATA
dtflw-0.6.7.dist-info/WHEEL
dtflw-0.6.7.dist-info/top_level.txt
dtflw-0.6.7.dist-info/RECORD
